fmtree/__init__.py
fmtree/core/__init__.py
fmtree/core/constants.py
fmtree/core/filter.py
fmtree/core/format.py
fmtree/core/node.py
fmtree/core/scraper.py
fmtree/core/sorter.py
fmtree/core/utils.py
fmtree/image/__init__.py
fmtree/image/dup.py
fmtree/visualizer/__init__.py
fmtree/visualizer/image_dir.py
fmtree/visualizer/visualize.py
fmtree/visualizer/template/index.html
fmtree/visualizer/template/assets/bootstrap.bundle.min.js
fmtree/visualizer/template/assets/bootstrap.min.css
fmtree/visualizer/template/assets/bootstrap.min.js
fmtree/visualizer/template/assets/jquery-3.6.0.min.js
tests/__init__.py
tests/test_filter.py
fmtree-0.3.2.dist-info/LICENSE
fmtree-0.3.2.dist-info/METADATA
fmtree-0.3.2.dist-info/WHEEL
fmtree-0.3.2.dist-info/top_level.txt
fmtree-0.3.2.dist-info/RECORD
