Metadata-Version: 2.1
Name: fmtree
Version: 0.3.2
Summary: Scrape File System and output in different formats
Home-page: https://github.com/fmtree-dev/fmtree
Author: Huakun Shen
Author-email: huakun.shen@huakunshen.com
Project-URL: Bug Tracker, https://github.com/fmtree-dev/fmtree/issues
Project-URL: Documentation, https://fmtree-dev.github.io/fmtree/
Classifier: Programming Language :: Python :: 3
Classifier: License :: OSI Approved :: MIT License
Classifier: Operating System :: OS Independent
Requires-Python: >=3.8
License-File: LICENSE
